{
 "blueprint": {
  "icons": [
   {
    "signal": {
     "type": "item",
     "name": "stone-wall"
    },
    "index": 1
   },
   {
    "signal": {
     "type": "item",
     "name": "rail"
    },
    "index": 2
   }
  ],
  "entities": [
   {
    "entity_number": 1,
    "name": "rail-chain-signal",
    "position": {
     "x": -5.5,
     "y": -8.5
    },
    "control_behavior": {
     "red_output_signal": {
      "type": "virtual",
      "name": "signal-T"
     },
     "orange_output_signal": {
      "type": "virtual",
      "name": "signal-T"
     }
    },
    "connections": {
     "1": {
      "red": [
       {
        "entity_id": 9
       }
      ]
     }
    }
   },
   {
    "entity_number": 2,
    "name": "stone-wall",
    "position": {
     "x": -5.5,
     "y": -7.5
    }
   },
   {
    "entity_number": 3,
    "name": "stone-wall",
    "position": {
     "x": -6.5,
     "y": -7.5
    },
    "control_behavior": {
     "circuit_open_gate": true,
     "circuit_read_sensor": false,
     "circuit_condition": {
      "first_signal": {
       "type": "virtual",
       "name": "signal-T"
      },
      "constant": 0,
      "comparator": "="
     }
    },
    "connections": {
     "1": {
      "red": [
       {
        "entity_id": 9
       }
      ]
     }
    }
   },
   {
    "entity_number": 4,
    "name": "gate",
    "position": {
     "x": -3.5,
     "y": -7.5
    },
    "direction": 2
   },
   {
    "entity_number": 5,
    "name": "gate",
    "position": {
     "x": -4.5,
     "y": -7.5
    },
    "direction": 2
   },
   {
    "entity_number": 6,
    "name": "straight-rail",
    "position": {
     "x": -4,
     "y": -8
    }
   },
   {
    "entity_number": 7,
    "name": "stone-wall",
    "position": {
     "x": -2.5,
     "y": -7.5
    },
    "control_behavior": {
     "circuit_open_gate": true,
     "circuit_read_sensor": false,
     "circuit_condition": {
      "first_signal": {
       "type": "virtual",
       "name": "signal-T"
      },
      "constant": 0,
      "comparator": "\u2260"
     }
    },
    "connections": {
     "1": {
      "red": [
       {
        "entity_id": 9
       }
      ]
     }
    }
   },
   {
    "entity_number": 8,
    "name": "stone-wall",
    "position": {
     "x": -1.5,
     "y": -7.5
    },
    "control_behavior": {
     "circuit_open_gate": true,
     "circuit_read_sensor": false,
     "circuit_condition": {
      "first_signal": {
       "type": "virtual",
       "name": "signal-T"
      },
      "constant": 0,
      "comparator": "="
     }
    },
    "connections": {
     "1": {
      "red": [
       {
        "entity_id": 9
       }
      ]
     }
    }
   },
   {
    "entity_number": 9,
    "name": "small-electric-pole",
    "position": {
     "x": -2.5,
     "y": -8.5
    },
    "connections": {
     "1": {
      "red": [
       {
        "entity_id": 1
       },
       {
        "entity_id": 3
       },
       {
        "entity_id": 8
       },
       {
        "entity_id": 7
       },
       {
        "entity_id": 55
       }
      ]
     }
    }
   },
   {
    "entity_number": 10,
    "name": "stone-wall",
    "position": {
     "x": -0.5,
     "y": -7.5
    }
   },
   {
    "entity_number": 11,
    "name": "stone-wall",
    "position": {
     "x": 0.5,
     "y": -7.5
    }
   },
   {
    "entity_number": 12,
    "name": "small-electric-pole",
    "position": {
     "x": 2.5,
     "y": -8.5
    },
    "connections": {
     "1": {
      "red": [
       {
        "entity_id": 13
       },
       {
        "entity_id": 61
       }
      ]
     }
    }
   },
   {
    "entity_number": 13,
    "name": "stone-wall",
    "position": {
     "x": 2.5,
     "y": -7.5
    },
    "control_behavior": {
     "circuit_open_gate": true,
     "circuit_read_sensor": false,
     "circuit_condition": {
      "first_signal": {
       "type": "virtual",
       "name": "signal-T"
      },
      "constant": 0,
      "comparator": "\u2260"
     }
    },
    "connections": {
     "1": {
      "red": [
       {
        "entity_id": 12
       }
      ]
     }
    }
   },
   {
    "entity_number": 14,
    "name": "stone-wall",
    "position": {
     "x": 1.5,
     "y": -7.5
    },
    "control_behavior": {
     "circuit_open_gate": true,
     "circuit_read_sensor": false,
     "circuit_condition": {
      "first_signal": {
       "type": "virtual",
       "name": "signal-T"
      },
      "constant": 0,
      "comparator": "="
     }
    }
   },
   {
    "entity_number": 15,
    "name": "gate",
    "position": {
     "x": 4.5,
     "y": -7.5
    },
    "direction": 2
   },
   {
    "entity_number": 16,
    "name": "gate",
    "position": {
     "x": 3.5,
     "y": -7.5
    },
    "direction": 2
   },
   {
    "entity_number": 17,
    "name": "straight-rail",
    "position": {
     "x": 4,
     "y": -8
    }
   },
   {
    "entity_number": 18,
    "name": "stone-wall",
    "position": {
     "x": 6.5,
     "y": -7.5
    }
   },
   {
    "entity_number": 19,
    "name": "stone-wall",
    "position": {
     "x": 5.5,
     "y": -7.5
    }
   },
   {
    "entity_number": 20,
    "name": "gate",
    "position": {
     "x": -6.5,
     "y": -6.5
    }
   },
   {
    "entity_number": 21,
    "name": "gate",
    "position": {
     "x": -6.5,
     "y": -5.5
    }
   },
   {
    "entity_number": 22,
    "name": "straight-rail",
    "position": {
     "x": -4,
     "y": -6
    }
   },
   {
    "entity_number": 23,
    "name": "gate",
    "position": {
     "x": -1.5,
     "y": -6.5
    }
   },
   {
    "entity_number": 24,
    "name": "gate",
    "position": {
     "x": -1.5,
     "y": -5.5
    }
   },
   {
    "entity_number": 25,
    "name": "gate",
    "position": {
     "x": 1.5,
     "y": -6.5
    }
   },
   {
    "entity_number": 26,
    "name": "gate",
    "position": {
     "x": 1.5,
     "y": -5.5
    }
   },
   {
    "entity_number": 27,
    "name": "straight-rail",
    "position": {
     "x": 4,
     "y": -6
    }
   },
   {
    "entity_number": 28,
    "name": "gate",
    "position": {
     "x": 6.5,
     "y": -6.5
    }
   },
   {
    "entity_number": 29,
    "name": "gate",
    "position": {
     "x": 6.5,
     "y": -5.5
    }
   },
   {
    "entity_number": 30,
    "name": "gate",
    "position": {
     "x": -6.5,
     "y": -4.5
    }
   },
   {
    "entity_number": 31,
    "name": "gate",
    "position": {
     "x": -6.5,
     "y": -3.5
    }
   },
   {
    "entity_number": 32,
    "name": "straight-rail",
    "position": {
     "x": -4,
     "y": -4
    }
   },
   {
    "entity_number": 33,
    "name": "gate",
    "position": {
     "x": -1.5,
     "y": -4.5
    }
   },
   {
    "entity_number": 34,
    "name": "gate",
    "position": {
     "x": -1.5,
     "y": -3.5
    }
   },
   {
    "entity_number": 35,
    "name": "gate",
    "position": {
     "x": 1.5,
     "y": -4.5
    }
   },
   {
    "entity_number": 36,
    "name": "gate",
    "position": {
     "x": 1.5,
     "y": -3.5
    }
   },
   {
    "entity_number": 37,
    "name": "straight-rail",
    "position": {
     "x": 4,
     "y": -4
    }
   },
   {
    "entity_number": 38,
    "name": "gate",
    "position": {
     "x": 6.5,
     "y": -3.5
    }
   },
   {
    "entity_number": 39,
    "name": "gate",
    "position": {
     "x": 6.5,
     "y": -4.5
    }
   },
   {
    "entity_number": 40,
    "name": "stone-wall",
    "position": {
     "x": -11.5,
     "y": -1.5
    }
   },
   {
    "entity_number": 41,
    "name": "stone-wall",
    "position": {
     "x": -11.5,
     "y": -2.5
    }
   },
   {
    "entity_number": 42,
    "name": "pipe-to-ground",
    "position": {
     "x": -9.5,
     "y": -1.5
    },
    "direction": 6
   },
   {
    "entity_number": 43,
    "name": "pipe-to-ground",
    "position": {
     "x": -10.5,
     "y": -1.5
    },
    "direction": 2
   },
   {
    "entity_number": 44,
    "name": "stone-wall",
    "position": {
     "x": -9.5,
     "y": -2.5
    }
   },
   {
    "entity_number": 45,
    "name": "stone-wall",
    "position": {
     "x": -10.5,
     "y": -2.5
    }
   },
   {
    "entity_number": 46,
    "name": "stone-wall",
    "position": {
     "x": -7.5,
     "y": -2.5
    }
   },
   {
    "entity_number": 47,
    "name": "stone-wall",
    "position": {
     "x": -8.5,
     "y": -2.5
    }
   },
   {
    "entity_number": 48,
    "name": "small-electric-pole",
    "position": {
     "x": -8.5,
     "y": -1.5
    }
   },
   {
    "entity_number": 49,
    "name": "stone-wall",
    "position": {
     "x": -5.5,
     "y": -2.5
    }
   },
   {
    "entity_number": 50,
    "name": "stone-wall",
    "position": {
     "x": -6.5,
     "y": -2.5
    }
   },
   {
    "entity_number": 51,
    "name": "gate",
    "position": {
     "x": -3.5,
     "y": -2.5
    },
    "direction": 2
   },
   {
    "entity_number": 52,
    "name": "gate",
    "position": {
     "x": -4.5,
     "y": -2.5
    },
    "direction": 2
   },
   {
    "entity_number": 53,
    "name": "straight-rail",
    "position": {
     "x": -4,
     "y": -2
    }
   },
   {
    "entity_number": 54,
    "name": "stone-wall",
    "position": {
     "x": -1.5,
     "y": -2.5
    },
    "control_behavior": {
     "circuit_open_gate": true,
     "circuit_read_sensor": false,
     "circuit_condition": {
      "first_signal": {
       "type": "virtual",
       "name": "signal-T"
      },
      "constant": 0,
      "comparator": "="
     }
    }
   },
   {
    "entity_number": 55,
    "name": "small-electric-pole",
    "position": {
     "x": -2.5,
     "y": -1.5
    },
    "connections": {
     "1": {
      "red": [
       {
        "entity_id": 9
       },
       {
        "entity_id": 56
       }
      ]
     }
    }
   },
   {
    "entity_number": 56,
    "name": "stone-wall",
    "position": {
     "x": -2.5,
     "y": -2.5
    },
    "control_behavior": {
     "circuit_open_gate": true,
     "circuit_read_sensor": false,
     "circuit_condition": {
      "first_signal": {
       "type": "virtual",
       "name": "signal-T"
      },
      "constant": 0,
      "comparator": "\u2260"
     }
    },
    "connections": {
     "1": {
      "red": [
       {
        "entity_id": 55
       }
      ]
     }
    }
   },
   {
    "entity_number": 57,
    "name": "pipe-to-ground",
    "position": {
     "x": 0.5,
     "y": -1.5
    },
    "direction": 6
   },
   {
    "entity_number": 58,
    "name": "pipe-to-ground",
    "position": {
     "x": -0.5,
     "y": -1.5
    },
    "direction": 2
   },
   {
    "entity_number": 59,
    "name": "stone-wall",
    "position": {
     "x": -0.5,
     "y": -2.5
    }
   },
   {
    "entity_number": 60,
    "name": "stone-wall",
    "position": {
     "x": 0.5,
     "y": -2.5
    }
   },
   {
    "entity_number": 61,
    "name": "small-electric-pole",
    "position": {
     "x": 2.5,
     "y": -1.5
    },
    "connections": {
     "1": {
      "red": [
       {
        "entity_id": 12
       },
       {
        "entity_id": 62
       },
       {
        "entity_id": 63
       },
       {
        "entity_id": 67
       },
       {
        "entity_id": 69
       }
      ]
     }
    }
   },
   {
    "entity_number": 62,
    "name": "stone-wall",
    "position": {
     "x": 2.5,
     "y": -2.5
    },
    "control_behavior": {
     "circuit_open_gate": true,
     "circuit_read_sensor": false,
     "circuit_condition": {
      "first_signal": {
       "type": "virtual",
       "name": "signal-T"
      },
      "constant": 0,
      "comparator": "\u2260"
     }
    },
    "connections": {
     "1": {
      "red": [
       {
        "entity_id": 61
       }
      ]
     }
    }
   },
   {
    "entity_number": 63,
    "name": "stone-wall",
    "position": {
     "x": 1.5,
     "y": -2.5
    },
    "control_behavior": {
     "circuit_open_gate": true,
     "circuit_read_sensor": false,
     "circuit_condition": {
      "first_signal": {
       "type": "virtual",
       "name": "signal-T"
      },
      "constant": 0,
      "comparator": "="
     }
    },
    "connections": {
     "1": {
      "red": [
       {
        "entity_id": 61
       }
      ]
     }
    }
   },
   {
    "entity_number": 64,
    "name": "gate",
    "position": {
     "x": 4.5,
     "y": -2.5
    },
    "direction": 2
   },
   {
    "entity_number": 65,
    "name": "gate",
    "position": {
     "x": 3.5,
     "y": -2.5
    },
    "direction": 2
   },
   {
    "entity_number": 66,
    "name": "straight-rail",
    "position": {
     "x": 4,
     "y": -2
    }
   },
   {
    "entity_number": 67,
    "name": "stone-wall",
    "position": {
     "x": 6.5,
     "y": -2.5
    },
    "control_behavior": {
     "circuit_open_gate": true,
     "circuit_read_sensor": false,
     "circuit_condition": {
      "first_signal": {
       "type": "virtual",
       "name": "signal-T"
      },
      "constant": 0,
      "comparator": "="
     }
    },
    "connections": {
     "1": {
      "red": [
       {
        "entity_id": 61
       }
      ]
     }
    }
   },
   {
    "entity_number": 68,
    "name": "stone-wall",
    "position": {
     "x": 5.5,
     "y": -2.5
    }
   },
   {
    "entity_number": 69,
    "name": "rail-chain-signal",
    "position": {
     "x": 5.5,
     "y": -1.5
    },
    "direction": 4,
    "control_behavior": {
     "red_output_signal": {
      "type": "virtual",
      "name": "signal-T"
     },
     "orange_output_signal": {
      "type": "virtual",
      "name": "signal-T"
     }
    },
    "connections": {
     "1": {
      "red": [
       {
        "entity_id": 61
       }
      ]
     }
    }
   },
   {
    "entity_number": 70,
    "name": "small-electric-pole",
    "position": {
     "x": 8.5,
     "y": -1.5
    }
   },
   {
    "entity_number": 71,
    "name": "stone-wall",
    "position": {
     "x": 8.5,
     "y": -2.5
    }
   },
   {
    "entity_number": 72,
    "name": "stone-wall",
    "position": {
     "x": 7.5,
     "y": -2.5
    }
   },
   {
    "entity_number": 73,
    "name": "pipe-to-ground",
    "position": {
     "x": 10.5,
     "y": -1.5
    },
    "direction": 6
   },
   {
    "entity_number": 74,
    "name": "pipe-to-ground",
    "position": {
     "x": 9.5,
     "y": -1.5
    },
    "direction": 2
   },
   {
    "entity_number": 75,
    "name": "stone-wall",
    "position": {
     "x": 10.5,
     "y": -2.5
    }
   },
   {
    "entity_number": 76,
    "name": "stone-wall",
    "position": {
     "x": 9.5,
     "y": -2.5
    }
   },
   {
    "entity_number": 77,
    "name": "stone-wall",
    "position": {
     "x": 11.5,
     "y": -1.5
    }
   },
   {
    "entity_number": 78,
    "name": "stone-wall",
    "position": {
     "x": 11.5,
     "y": -2.5
    }
   },
   {
    "entity_number": 79,
    "name": "underground-belt",
    "position": {
     "x": -12.5,
     "y": -0.5
    },
    "direction": 2,
    "type": "input"
   },
   {
    "entity_number": 80,
    "name": "stone-wall",
    "position": {
     "x": -11.5,
     "y": 0.5
    }
   },
   {
    "entity_number": 81,
    "name": "underground-belt",
    "position": {
     "x": -12.5,
     "y": 0.5
    },
    "direction": 6,
    "type": "output"
   },
   {
    "entity_number": 82,
    "name": "stone-wall",
    "position": {
     "x": -11.5,
     "y": -0.5
    }
   },
   {
    "entity_number": 83,
    "name": "transport-belt",
    "position": {
     "x": -9.5,
     "y": -0.5
    },
    "direction": 2
   },
   {
    "entity_number": 84,
    "name": "underground-belt",
    "position": {
     "x": -9.5,
     "y": 0.5
    },
    "direction": 6,
    "type": "output"
   },
   {
    "entity_number": 85,
    "name": "underground-belt",
    "position": {
     "x": -10.5,
     "y": 0.5
    },
    "direction": 6,
    "type": "input"
   },
   {
    "entity_number": 86,
    "name": "underground-belt",
    "position": {
     "x": -10.5,
     "y": -0.5
    },
    "direction": 2,
    "type": "output"
   },
   {
    "entity_number": 87,
    "name": "transport-belt",
    "position": {
     "x": -8.5,
     "y": -0.5
    },
    "direction": 2
   },
   {
    "entity_number": 88,
    "name": "transport-belt",
    "position": {
     "x": -7.5,
     "y": -0.5
    },
    "direction": 2
   },
   {
    "entity_number": 89,
    "name": "burner-inserter",
    "position": {
     "x": -7.5,
     "y": 0.5
    }
   },
   {
    "entity_number": 90,
    "name": "burner-inserter",
    "position": {
     "x": -8.5,
     "y": 0.5
    }
   },
   {
    "entity_number": 91,
    "name": "transport-belt",
    "position": {
     "x": -6.5,
     "y": -0.5
    },
    "direction": 2
   },
   {
    "entity_number": 92,
    "name": "underground-belt",
    "position": {
     "x": -5.5,
     "y": 0.5
    },
    "direction": 6,
    "type": "output"
   },
   {
    "entity_number": 93,
    "name": "underground-belt",
    "position": {
     "x": -5.5,
     "y": -0.5
    },
    "direction": 2,
    "type": "input"
   },
   {
    "entity_number": 94,
    "name": "underground-belt",
    "position": {
     "x": -6.5,
     "y": 0.5
    },
    "direction": 6,
    "type": "input"
   },
   {
    "entity_number": 95,
    "name": "straight-rail",
    "position": {
     "x": -4,
     "y": 0
    }
   },
   {
    "entity_number": 96,
    "name": "transport-belt",
    "position": {
     "x": -1.5,
     "y": -0.5
    },
    "direction": 2
   },
   {
    "entity_number": 97,
    "name": "underground-belt",
    "position": {
     "x": -1.5,
     "y": 0.5
    },
    "direction": 6,
    "type": "output"
   },
   {
    "entity_number": 98,
    "name": "underground-belt",
    "position": {
     "x": -2.5,
     "y": 0.5
    },
    "direction": 6,
    "type": "input"
   },
   {
    "entity_number": 99,
    "name": "underground-belt",
    "position": {
     "x": -2.5,
     "y": -0.5
    },
    "direction": 2,
    "type": "output"
   },
   {
    "entity_number": 100,
    "name": "transport-belt",
    "position": {
     "x": -0.5,
     "y": -0.5
    },
    "direction": 2
   },
   {
    "entity_number": 101,
    "name": "transport-belt",
    "position": {
     "x": 0.5,
     "y": -0.5
    },
    "direction": 2
   },
   {
    "entity_number": 102,
    "name": "burner-inserter",
    "position": {
     "x": 0.5,
     "y": 0.5
    }
   },
   {
    "entity_number": 103,
    "name": "burner-inserter",
    "position": {
     "x": -0.5,
     "y": 0.5
    }
   },
   {
    "entity_number": 104,
    "name": "transport-belt",
    "position": {
     "x": 1.5,
     "y": -0.5
    },
    "direction": 2
   },
   {
    "entity_number": 105,
    "name": "underground-belt",
    "position": {
     "x": 2.5,
     "y": 0.5
    },
    "direction": 6,
    "type": "output"
   },
   {
    "entity_number": 106,
    "name": "underground-belt",
    "position": {
     "x": 2.5,
     "y": -0.5
    },
    "direction": 2,
    "type": "input"
   },
   {
    "entity_number": 107,
    "name": "underground-belt",
    "position": {
     "x": 1.5,
     "y": 0.5
    },
    "direction": 6,
    "type": "input"
   },
   {
    "entity_number": 108,
    "name": "straight-rail",
    "position": {
     "x": 4,
     "y": 0
    }
   },
   {
    "entity_number": 109,
    "name": "underground-belt",
    "position": {
     "x": 6.5,
     "y": 0.5
    },
    "direction": 6,
    "type": "output"
   },
   {
    "entity_number": 110,
    "name": "transport-belt",
    "position": {
     "x": 6.5,
     "y": -0.5
    },
    "direction": 2
   },
   {
    "entity_number": 111,
    "name": "underground-belt",
    "position": {
     "x": 5.5,
     "y": -0.5
    },
    "direction": 2,
    "type": "output"
   },
   {
    "entity_number": 112,
    "name": "underground-belt",
    "position": {
     "x": 5.5,
     "y": 0.5
    },
    "direction": 6,
    "type": "input"
   },
   {
    "entity_number": 113,
    "name": "transport-belt",
    "position": {
     "x": 8.5,
     "y": -0.5
    },
    "direction": 2
   },
   {
    "entity_number": 114,
    "name": "burner-inserter",
    "position": {
     "x": 8.5,
     "y": 0.5
    }
   },
   {
    "entity_number": 115,
    "name": "burner-inserter",
    "position": {
     "x": 7.5,
     "y": 0.5
    }
   },
   {
    "entity_number": 116,
    "name": "transport-belt",
    "position": {
     "x": 7.5,
     "y": -0.5
    },
    "direction": 2
   },
   {
    "entity_number": 117,
    "name": "underground-belt",
    "position": {
     "x": 10.5,
     "y": -0.5
    },
    "direction": 2,
    "type": "input"
   },
   {
    "entity_number": 118,
    "name": "underground-belt",
    "position": {
     "x": 10.5,
     "y": 0.5
    },
    "direction": 6,
    "type": "output"
   },
   {
    "entity_number": 119,
    "name": "transport-belt",
    "position": {
     "x": 9.5,
     "y": -0.5
    },
    "direction": 2
   },
   {
    "entity_number": 120,
    "name": "underground-belt",
    "position": {
     "x": 9.5,
     "y": 0.5
    },
    "direction": 6,
    "type": "input"
   },
   {
    "entity_number": 121,
    "name": "stone-wall",
    "position": {
     "x": 11.5,
     "y": 0.5
    }
   },
   {
    "entity_number": 122,
    "name": "stone-wall",
    "position": {
     "x": 11.5,
     "y": -0.5
    }
   },
   {
    "entity_number": 123,
    "name": "underground-belt",
    "position": {
     "x": 12.5,
     "y": 0.5
    },
    "direction": 6,
    "type": "input"
   },
   {
    "entity_number": 124,
    "name": "underground-belt",
    "position": {
     "x": 12.5,
     "y": -0.5
    },
    "direction": 2,
    "type": "output"
   },
   {
    "entity_number": 125,
    "name": "stone-wall",
    "position": {
     "x": -11.5,
     "y": 1.5
    }
   },
   {
    "entity_number": 126,
    "name": "stone-wall",
    "position": {
     "x": -11.5,
     "y": 2.5
    }
   },
   {
    "entity_number": 127,
    "name": "gun-turret",
    "position": {
     "x": -9,
     "y": 2
    },
    "direction": 4
   },
   {
    "entity_number": 128,
    "name": "gun-turret",
    "position": {
     "x": -7,
     "y": 2
    },
    "direction": 4
   },
   {
    "entity_number": 129,
    "name": "rail-chain-signal",
    "position": {
     "x": -5.5,
     "y": 2.5
    },
    "control_behavior": {
     "red_output_signal": {
      "type": "virtual",
      "name": "signal-T"
     },
     "orange_output_signal": {
      "type": "virtual",
      "name": "signal-T"
     }
    },
    "connections": {
     "1": {
      "red": [
       {
        "entity_id": 150
       }
      ]
     }
    }
   },
   {
    "entity_number": 130,
    "name": "straight-rail",
    "position": {
     "x": -4,
     "y": 2
    }
   },
   {
    "entity_number": 131,
    "name": "gun-turret",
    "position": {
     "x": -1,
     "y": 2
    },
    "direction": 4
   },
   {
    "entity_number": 132,
    "name": "gun-turret",
    "position": {
     "x": 1,
     "y": 2
    },
    "direction": 4
   },
   {
    "entity_number": 133,
    "name": "straight-rail",
    "position": {
     "x": 4,
     "y": 2
    }
   },
   {
    "entity_number": 134,
    "name": "gun-turret",
    "position": {
     "x": 7,
     "y": 2
    },
    "direction": 4
   },
   {
    "entity_number": 135,
    "name": "gun-turret",
    "position": {
     "x": 9,
     "y": 2
    },
    "direction": 4
   },
   {
    "entity_number": 136,
    "name": "stone-wall",
    "position": {
     "x": 11.5,
     "y": 2.5
    }
   },
   {
    "entity_number": 137,
    "name": "stone-wall",
    "position": {
     "x": 11.5,
     "y": 1.5
    }
   },
   {
    "entity_number": 138,
    "name": "stone-wall",
    "position": {
     "x": -12.5,
     "y": 3.5
    }
   },
   {
    "entity_number": 139,
    "name": "stone-wall",
    "position": {
     "x": -12.5,
     "y": 4.5
    }
   },
   {
    "entity_number": 140,
    "name": "stone-wall",
    "position": {
     "x": -11.5,
     "y": 4.5
    }
   },
   {
    "entity_number": 141,
    "name": "stone-wall",
    "position": {
     "x": -11.5,
     "y": 3.5
    }
   },
   {
    "entity_number": 142,
    "name": "stone-wall",
    "position": {
     "x": -10.5,
     "y": 3.5
    }
   },
   {
    "entity_number": 143,
    "name": "stone-wall",
    "position": {
     "x": -10.5,
     "y": 4.5
    }
   },
   {
    "entity_number": 144,
    "name": "stone-wall",
    "position": {
     "x": -9.5,
     "y": 3.5
    }
   },
   {
    "entity_number": 145,
    "name": "stone-wall",
    "position": {
     "x": -9.5,
     "y": 4.5
    }
   },
   {
    "entity_number": 146,
    "name": "stone-wall",
    "position": {
     "x": -8.5,
     "y": 4.5
    }
   },
   {
    "entity_number": 147,
    "name": "stone-wall",
    "position": {
     "x": -8.5,
     "y": 3.5
    }
   },
   {
    "entity_number": 148,
    "name": "stone-wall",
    "position": {
     "x": -7.5,
     "y": 4.5
    }
   },
   {
    "entity_number": 149,
    "name": "stone-wall",
    "position": {
     "x": -7.5,
     "y": 3.5
    }
   },
   {
    "entity_number": 150,
    "name": "stone-wall",
    "position": {
     "x": -5.5,
     "y": 3.5
    },
    "control_behavior": {
     "circuit_open_gate": true,
     "circuit_read_sensor": false,
     "circuit_condition": {
      "first_signal": {
       "type": "virtual",
       "name": "signal-T"
      },
      "constant": 0,
      "comparator": "\u2260"
     }
    },
    "connections": {
     "1": {
      "red": [
       {
        "entity_id": 129
       },
       {
        "entity_id": 151
       }
      ]
     }
    }
   },
   {
    "entity_number": 151,
    "name": "stone-wall",
    "position": {
     "x": -5.5,
     "y": 4.5
    },
    "control_behavior": {
     "circuit_open_gate": true,
     "circuit_read_sensor": false,
     "circuit_condition": {
      "first_signal": {
       "type": "virtual",
       "name": "signal-T"
      },
      "constant": 0,
      "comparator": "\u2260"
     }
    },
    "connections": {
     "1": {
      "red": [
       {
        "entity_id": 150
       }
      ]
     }
    }
   },
   {
    "entity_number": 152,
    "name": "stone-wall",
    "position": {
     "x": -6.5,
     "y": 4.5
    }
   },
   {
    "entity_number": 153,
    "name": "stone-wall",
    "position": {
     "x": -6.5,
     "y": 3.5
    }
   },
   {
    "entity_number": 154,
    "name": "straight-rail",
    "position": {
     "x": -4,
     "y": 4
    }
   },
   {
    "entity_number": 155,
    "name": "gate",
    "position": {
     "x": -3.5,
     "y": 4.5
    },
    "direction": 2
   },
   {
    "entity_number": 156,
    "name": "gate",
    "position": {
     "x": -3.5,
     "y": 3.5
    },
    "direction": 2
   },
   {
    "entity_number": 157,
    "name": "gate",
    "position": {
     "x": -4.5,
     "y": 4.5
    },
    "direction": 2
   },
   {
    "entity_number": 158,
    "name": "gate",
    "position": {
     "x": -4.5,
     "y": 3.5
    },
    "direction": 2
   },
   {
    "entity_number": 159,
    "name": "stone-wall",
    "position": {
     "x": -1.5,
     "y": 4.5
    }
   },
   {
    "entity_number": 160,
    "name": "stone-wall",
    "position": {
     "x": -1.5,
     "y": 3.5
    }
   },
   {
    "entity_number": 161,
    "name": "stone-wall",
    "position": {
     "x": -2.5,
     "y": 4.5
    }
   },
   {
    "entity_number": 162,
    "name": "stone-wall",
    "position": {
     "x": -2.5,
     "y": 3.5
    }
   },
   {
    "entity_number": 163,
    "name": "stone-wall",
    "position": {
     "x": 0.5,
     "y": 4.5
    }
   },
   {
    "entity_number": 164,
    "name": "stone-wall",
    "position": {
     "x": 0.5,
     "y": 3.5
    }
   },
   {
    "entity_number": 165,
    "name": "stone-wall",
    "position": {
     "x": -0.5,
     "y": 4.5
    }
   },
   {
    "entity_number": 166,
    "name": "stone-wall",
    "position": {
     "x": -0.5,
     "y": 3.5
    }
   },
   {
    "entity_number": 167,
    "name": "stone-wall",
    "position": {
     "x": 2.5,
     "y": 3.5
    }
   },
   {
    "entity_number": 168,
    "name": "stone-wall",
    "position": {
     "x": 2.5,
     "y": 4.5
    }
   },
   {
    "entity_number": 169,
    "name": "stone-wall",
    "position": {
     "x": 1.5,
     "y": 3.5
    }
   },
   {
    "entity_number": 170,
    "name": "stone-wall",
    "position": {
     "x": 1.5,
     "y": 4.5
    }
   },
   {
    "entity_number": 171,
    "name": "gate",
    "position": {
     "x": 4.5,
     "y": 4.5
    },
    "direction": 2
   },
   {
    "entity_number": 172,
    "name": "gate",
    "position": {
     "x": 3.5,
     "y": 4.5
    },
    "direction": 2
   },
   {
    "entity_number": 173,
    "name": "gate",
    "position": {
     "x": 3.5,
     "y": 3.5
    },
    "direction": 2
   },
   {
    "entity_number": 174,
    "name": "gate",
    "position": {
     "x": 4.5,
     "y": 3.5
    },
    "direction": 2
   },
   {
    "entity_number": 175,
    "name": "straight-rail",
    "position": {
     "x": 4,
     "y": 4
    }
   },
   {
    "entity_number": 176,
    "name": "stone-wall",
    "position": {
     "x": 6.5,
     "y": 4.5
    }
   },
   {
    "entity_number": 177,
    "name": "stone-wall",
    "position": {
     "x": 6.5,
     "y": 3.5
    }
   },
   {
    "entity_number": 178,
    "name": "stone-wall",
    "position": {
     "x": 5.5,
     "y": 3.5
    },
    "control_behavior": {
     "circuit_open_gate": true,
     "circuit_read_sensor": false,
     "circuit_condition": {
      "first_signal": {
       "type": "virtual",
       "name": "signal-T"
      },
      "constant": 0,
      "comparator": "\u2260"
     }
    },
    "connections": {
     "1": {
      "red": [
       {
        "entity_id": 179
       }
      ]
     }
    }
   },
   {
    "entity_number": 179,
    "name": "stone-wall",
    "position": {
     "x": 5.5,
     "y": 4.5
    },
    "control_behavior": {
     "circuit_open_gate": true,
     "circuit_read_sensor": false,
     "circuit_condition": {
      "first_signal": {
       "type": "virtual",
       "name": "signal-T"
      },
      "constant": 0,
      "comparator": "\u2260"
     }
    },
    "connections": {
     "1": {
      "red": [
       {
        "entity_id": 178
       },
       {
        "entity_id": 194
       }
      ]
     }
    }
   },
   {
    "entity_number": 180,
    "name": "stone-wall",
    "position": {
     "x": 8.5,
     "y": 3.5
    }
   },
   {
    "entity_number": 181,
    "name": "stone-wall",
    "position": {
     "x": 8.5,
     "y": 4.5
    }
   },
   {
    "entity_number": 182,
    "name": "stone-wall",
    "position": {
     "x": 7.5,
     "y": 4.5
    }
   },
   {
    "entity_number": 183,
    "name": "stone-wall",
    "position": {
     "x": 7.5,
     "y": 3.5
    }
   },
   {
    "entity_number": 184,
    "name": "stone-wall",
    "position": {
     "x": 10.5,
     "y": 3.5
    }
   },
   {
    "entity_number": 185,
    "name": "stone-wall",
    "position": {
     "x": 10.5,
     "y": 4.5
    }
   },
   {
    "entity_number": 186,
    "name": "stone-wall",
    "position": {
     "x": 9.5,
     "y": 3.5
    }
   },
   {
    "entity_number": 187,
    "name": "stone-wall",
    "position": {
     "x": 9.5,
     "y": 4.5
    }
   },
   {
    "entity_number": 188,
    "name": "stone-wall",
    "position": {
     "x": 12.5,
     "y": 4.5
    }
   },
   {
    "entity_number": 189,
    "name": "stone-wall",
    "position": {
     "x": 12.5,
     "y": 3.5
    }
   },
   {
    "entity_number": 190,
    "name": "stone-wall",
    "position": {
     "x": 11.5,
     "y": 4.5
    }
   },
   {
    "entity_number": 191,
    "name": "stone-wall",
    "position": {
     "x": 11.5,
     "y": 3.5
    }
   },
   {
    "entity_number": 192,
    "name": "straight-rail",
    "position": {
     "x": -4,
     "y": 6
    }
   },
   {
    "entity_number": 193,
    "name": "straight-rail",
    "position": {
     "x": 4,
     "y": 6
    }
   },
   {
    "entity_number": 194,
    "name": "rail-chain-signal",
    "position": {
     "x": 5.5,
     "y": 5.5
    },
    "direction": 4,
    "control_behavior": {
     "red_output_signal": {
      "type": "virtual",
      "name": "signal-T"
     },
     "orange_output_signal": {
      "type": "virtual",
      "name": "signal-T"
     }
    },
    "connections": {
     "1": {
      "red": [
       {
        "entity_id": 179
       }
      ]
     }
    }
   }
  ],
  "tiles": [
   {
    "position": {
     "x": -13,
     "y": -7
    },
    "name": "refined-concrete"
   },
   {
    "position": {
     "x": -13,
     "y": -6
    },
    "name": "refined-concrete"
   },
   {
    "position": {
     "x": -13,
     "y": -5
    },
    "name": "refined-concrete"
   },
   {
    "position": {
     "x": -13,
     "y": -4
    },
    "name": "refined-concrete"
   },
   {
    "position": {
     "x": -12,
     "y": -7
    },
    "name": "refined-concrete"
   },
   {
    "position": {
     "x": -12,
     "y": -6
    },
    "name": "refined-concrete"
   },
   {
    "position": {
     "x": -12,
     "y": -5
    },
    "name": "refined-concrete"
   },
   {
    "position": {
     "x": -12,
     "y": -4
    },
    "name": "refined-concrete"
   },
   {
    "position": {
     "x": -11,
     "y": -7
    },
    "name": "refined-concrete"
   },
   {
    "position": {
     "x": -11,
     "y": -6
    },
    "name": "refined-concrete"
   },
   {
    "position": {
     "x": -11,
     "y": -5
    },
    "name": "refined-concrete"
   },
   {
    "position": {
     "x": -11,
     "y": -4
    },
    "name": "refined-concrete"
   },
   {
    "position": {
     "x": -10,
     "y": -7
    },
    "name": "refined-concrete"
   },
   {
    "position": {
     "x": -10,
     "y": -6
    },
    "name": "refined-concrete"
   },
   {
    "position": {
     "x": -10,
     "y": -5
    },
    "name": "refined-concrete"
   },
   {
    "position": {
     "x": -10,
     "y": -4
    },
    "name": "refined-concrete"
   },
   {
    "position": {
     "x": -9,
     "y": -7
    },
    "name": "refined-concrete"
   },
   {
    "position": {
     "x": -9,
     "y": -6
    },
    "name": "refined-concrete"
   },
   {
    "position": {
     "x": -9,
     "y": -5
    },
    "name": "refined-concrete"
   },
   {
    "position": {
     "x": -9,
     "y": -4
    },
    "name": "refined-concrete"
   },
   {
    "position": {
     "x": -8,
     "y": -7
    },
    "name": "refined-hazard-concrete-right"
   },
   {
    "position": {
     "x": -8,
     "y": -6
    },
    "name": "refined-hazard-concrete-right"
   },
   {
    "position": {
     "x": -8,
     "y": -5
    },
    "name": "refined-hazard-concrete-right"
   },
   {
    "position": {
     "x": -8,
     "y": -4
    },
    "name": "refined-hazard-concrete-right"
   },
   {
    "position": {
     "x": -7,
     "y": -7
    },
    "name": "refined-hazard-concrete-right"
   },
   {
    "position": {
     "x": -7,
     "y": -6
    },
    "name": "refined-hazard-concrete-right"
   },
   {
    "position": {
     "x": -7,
     "y": -5
    },
    "name": "refined-hazard-concrete-right"
   },
   {
    "position": {
     "x": -7,
     "y": -4
    },
    "name": "refined-hazard-concrete-right"
   },
   {
    "position": {
     "x": -6,
     "y": -7
    },
    "name": "refined-hazard-concrete-right"
   },
   {
    "position": {
     "x": -6,
     "y": -6
    },
    "name": "refined-hazard-concrete-right"
   },
   {
    "position": {
     "x": -6,
     "y": -5
    },
    "name": "refined-hazard-concrete-right"
   },
   {
    "position": {
     "x": -6,
     "y": -4
    },
    "name": "refined-hazard-concrete-right"
   },
   {
    "position": {
     "x": -5,
     "y": -7
    },
    "name": "refined-hazard-concrete-right"
   },
   {
    "position": {
     "x": -5,
     "y": -6
    },
    "name": "refined-hazard-concrete-right"
   },
   {
    "position": {
     "x": -5,
     "y": -5
    },
    "name": "refined-hazard-concrete-right"
   },
   {
    "position": {
     "x": -5,
     "y": -4
    },
    "name": "refined-hazard-concrete-right"
   },
   {
    "position": {
     "x": -4,
     "y": -7
    },
    "name": "refined-hazard-concrete-right"
   },
   {
    "position": {
     "x": -4,
     "y": -6
    },
    "name": "refined-hazard-concrete-right"
   },
   {
    "position": {
     "x": -4,
     "y": -5
    },
    "name": "refined-hazard-concrete-right"
   },
   {
    "position": {
     "x": -4,
     "y": -4
    },
    "name": "refined-hazard-concrete-right"
   },
   {
    "position": {
     "x": -3,
     "y": -7
    },
    "name": "refined-hazard-concrete-right"
   },
   {
    "position": {
     "x": -3,
     "y": -6
    },
    "name": "refined-hazard-concrete-right"
   },
   {
    "position": {
     "x": -3,
     "y": -5
    },
    "name": "refined-hazard-concrete-right"
   },
   {
    "position": {
     "x": -3,
     "y": -4
    },
    "name": "refined-hazard-concrete-right"
   },
   {
    "position": {
     "x": -2,
     "y": -7
    },
    "name": "refined-hazard-concrete-right"
   },
   {
    "position": {
     "x": -2,
     "y": -6
    },
    "name": "refined-hazard-concrete-right"
   },
   {
    "position": {
     "x": -2,
     "y": -5
    },
    "name": "refined-hazard-concrete-right"
   },
   {
    "position": {
     "x": -2,
     "y": -4
    },
    "name": "refined-hazard-concrete-right"
   },
   {
    "position": {
     "x": -1,
     "y": -7
    },
    "name": "refined-hazard-concrete-right"
   },
   {
    "position": {
     "x": -1,
     "y": -6
    },
    "name": "refined-hazard-concrete-right"
   },
   {
    "position": {
     "x": -1,
     "y": -5
    },
    "name": "refined-hazard-concrete-right"
   },
   {
    "position": {
     "x": -1,
     "y": -4
    },
    "name": "refined-hazard-concrete-right"
   },
   {
    "position": {
     "x": 0,
     "y": -7
    },
    "name": "refined-hazard-concrete-right"
   },
   {
    "position": {
     "x": 0,
     "y": -6
    },
    "name": "refined-hazard-concrete-right"
   },
   {
    "position": {
     "x": 0,
     "y": -5
    },
    "name": "refined-hazard-concrete-right"
   },
   {
    "position": {
     "x": 0,
     "y": -4
    },
    "name": "refined-hazard-concrete-right"
   },
   {
    "position": {
     "x": 1,
     "y": -7
    },
    "name": "refined-hazard-concrete-right"
   },
   {
    "position": {
     "x": 1,
     "y": -6
    },
    "name": "refined-hazard-concrete-right"
   },
   {
    "position": {
     "x": 1,
     "y": -5
    },
    "name": "refined-hazard-concrete-right"
   },
   {
    "position": {
     "x": 1,
     "y": -4
    },
    "name": "refined-hazard-concrete-right"
   },
   {
    "position": {
     "x": 2,
     "y": -7
    },
    "name": "refined-hazard-concrete-right"
   },
   {
    "position": {
     "x": 2,
     "y": -6
    },
    "name": "refined-hazard-concrete-right"
   },
   {
    "position": {
     "x": 2,
     "y": -5
    },
    "name": "refined-hazard-concrete-right"
   },
   {
    "position": {
     "x": 2,
     "y": -4
    },
    "name": "refined-hazard-concrete-right"
   },
   {
    "position": {
     "x": 3,
     "y": -7
    },
    "name": "refined-hazard-concrete-right"
   },
   {
    "position": {
     "x": 3,
     "y": -6
    },
    "name": "refined-hazard-concrete-right"
   },
   {
    "position": {
     "x": 3,
     "y": -5
    },
    "name": "refined-hazard-concrete-right"
   },
   {
    "position": {
     "x": 3,
     "y": -4
    },
    "name": "refined-hazard-concrete-right"
   },
   {
    "position": {
     "x": 4,
     "y": -7
    },
    "name": "refined-hazard-concrete-right"
   },
   {
    "position": {
     "x": 4,
     "y": -6
    },
    "name": "refined-hazard-concrete-right"
   },
   {
    "position": {
     "x": 4,
     "y": -5
    },
    "name": "refined-hazard-concrete-right"
   },
   {
    "position": {
     "x": 4,
     "y": -4
    },
    "name": "refined-hazard-concrete-right"
   },
   {
    "position": {
     "x": 5,
     "y": -7
    },
    "name": "refined-hazard-concrete-right"
   },
   {
    "position": {
     "x": 5,
     "y": -6
    },
    "name": "refined-hazard-concrete-right"
   },
   {
    "position": {
     "x": 5,
     "y": -5
    },
    "name": "refined-hazard-concrete-right"
   },
   {
    "position": {
     "x": 5,
     "y": -4
    },
    "name": "refined-hazard-concrete-right"
   },
   {
    "position": {
     "x": 6,
     "y": -7
    },
    "name": "refined-hazard-concrete-right"
   },
   {
    "position": {
     "x": 6,
     "y": -6
    },
    "name": "refined-hazard-concrete-right"
   },
   {
    "position": {
     "x": 6,
     "y": -5
    },
    "name": "refined-hazard-concrete-right"
   },
   {
    "position": {
     "x": 6,
     "y": -4
    },
    "name": "refined-hazard-concrete-right"
   },
   {
    "position": {
     "x": 7,
     "y": -7
    },
    "name": "refined-hazard-concrete-right"
   },
   {
    "position": {
     "x": 7,
     "y": -6
    },
    "name": "refined-hazard-concrete-right"
   },
   {
    "position": {
     "x": 7,
     "y": -5
    },
    "name": "refined-hazard-concrete-right"
   },
   {
    "position": {
     "x": 7,
     "y": -4
    },
    "name": "refined-hazard-concrete-right"
   },
   {
    "position": {
     "x": 8,
     "y": -7
    },
    "name": "refined-concrete"
   },
   {
    "position": {
     "x": 8,
     "y": -6
    },
    "name": "refined-concrete"
   },
   {
    "position": {
     "x": 8,
     "y": -5
    },
    "name": "refined-concrete"
   },
   {
    "position": {
     "x": 8,
     "y": -4
    },
    "name": "refined-concrete"
   },
   {
    "position": {
     "x": 9,
     "y": -7
    },
    "name": "refined-concrete"
   },
   {
    "position": {
     "x": 9,
     "y": -6
    },
    "name": "refined-concrete"
   },
   {
    "position": {
     "x": 9,
     "y": -5
    },
    "name": "refined-concrete"
   },
   {
    "position": {
     "x": 9,
     "y": -4
    },
    "name": "refined-concrete"
   },
   {
    "position": {
     "x": 10,
     "y": -7
    },
    "name": "refined-concrete"
   },
   {
    "position": {
     "x": 10,
     "y": -6
    },
    "name": "refined-concrete"
   },
   {
    "position": {
     "x": 10,
     "y": -5
    },
    "name": "refined-concrete"
   },
   {
    "position": {
     "x": 10,
     "y": -4
    },
    "name": "refined-concrete"
   },
   {
    "position": {
     "x": 11,
     "y": -7
    },
    "name": "refined-concrete"
   },
   {
    "position": {
     "x": 11,
     "y": -6
    },
    "name": "refined-concrete"
   },
   {
    "position": {
     "x": 11,
     "y": -5
    },
    "name": "refined-concrete"
   },
   {
    "position": {
     "x": 11,
     "y": -4
    },
    "name": "refined-concrete"
   },
   {
    "position": {
     "x": 12,
     "y": -7
    },
    "name": "refined-concrete"
   },
   {
    "position": {
     "x": 12,
     "y": -6
    },
    "name": "refined-concrete"
   },
   {
    "position": {
     "x": 12,
     "y": -5
    },
    "name": "refined-concrete"
   },
   {
    "position": {
     "x": 12,
     "y": -4
    },
    "name": "refined-concrete"
   }
  ],
  "item": "blueprint",
  "label": "Blox Wall Train Gate",
  "version": 73018245120
 }
}